OpsAi/OPs.py
OpsAi/__init__.py
OpsAi-0.3.dist-info/LICENSE
OpsAi-0.3.dist-info/METADATA
OpsAi-0.3.dist-info/WHEEL
OpsAi-0.3.dist-info/top_level.txt
OpsAi-0.3.dist-info/RECORD
