Metadata-Version: 2.1
Name: OpsAi
Version: 0.3
Summary: Ai Library for developer Ahmed Al-Awadi
Home-page: https://github.com/Ahmed-alawadi/OpsAi
Author: AHMED AL-AWADI
Author-email: dev.ahmed.alawadi@gmail.com
Classifier: Programming Language :: Python :: 3
Classifier: License :: OSI Approved :: MIT License
Classifier: Operating System :: OS Independent
Requires-Python: >=3.7
License-File: LICENSE
